slack_gfm/__init__.py
slack_gfm/exceptions.py
slack_gfm/py.typed
slack_gfm/ast/__init__.py
slack_gfm/ast/nodes.py
slack_gfm/ast/visitor.py
slack_gfm/parsers/__init__.py
slack_gfm/parsers/gfm.py
slack_gfm/parsers/mrkdwn.py
slack_gfm/parsers/rich_text.py
slack_gfm/renderers/__init__.py
slack_gfm/renderers/gfm.py
slack_gfm/renderers/gfm_visitor.py
slack_gfm/renderers/rich_text.py
slack_gfm/transformers/__init__.py
slack_gfm/transformers/mappings.py
slack_gfm-0.2.1.dist-info/METADATA
slack_gfm-0.2.1.dist-info/WHEEL
slack_gfm-0.2.1.dist-info/licenses/LICENSE
slack_gfm-0.2.1.dist-info/RECORD
