Metadata-Version: 2.4
Name: slack-gfm
Version: 0.2.1
Summary: Convert between Slack message formats (Mrkdwn, Rich Text) and GitHub Flavored Markdown with AST manipulation
Project-URL: Homepage, https://github.com/retcheverry/slack-gfm
Project-URL: Documentation, https://github.com/retcheverry/slack-gfm/tree/main/docs
Project-URL: Repository, https://github.com/retcheverry/slack-gfm
Project-URL: Issues, https://github.com/retcheverry/slack-gfm/issues
Author-email: Roberto Etcheverry <143276+retcheverry@users.noreply.github.com>
License: AGPL-3.0-or-later
License-File: LICENSE
Keywords: ast,converter,gfm,markdown,mrkdwn,rich-text,slack
Classifier: Development Status :: 3 - Alpha
Classifier: Intended Audience :: Developers
Classifier: License :: OSI Approved :: GNU Affero General Public License v3 or later (AGPLv3+)
Classifier: Programming Language :: Python :: 3
Classifier: Programming Language :: Python :: 3.12
Classifier: Topic :: Communications :: Chat
Classifier: Topic :: Software Development :: Libraries :: Python Modules
Classifier: Topic :: Text Processing :: Markup
Classifier: Typing :: Typed
Requires-Python: >=3.12
Requires-Dist: linkify-it-py>=2.0.3
Requires-Dist: markdown-it-py>=3.0.0
